{
  "app": {
    "[project]/Jth/Git Repository/Home/finance-home/app/_not-found/page": [
      "static/media/83afe278b6a6bb3c-s.p.3a6ba036.woff2"
    ],
    "[project]/Jth/Git Repository/Home/finance-home/app/admin/page": [
      "static/media/83afe278b6a6bb3c-s.p.3a6ba036.woff2"
    ],
    "[project]/Jth/Git Repository/Home/finance-home/app/login/page": [
      "static/media/83afe278b6a6bb3c-s.p.3a6ba036.woff2"
    ],
    "[project]/Jth/Git Repository/Home/finance-home/app/page": [
      "static/media/83afe278b6a6bb3c-s.p.3a6ba036.woff2"
    ],
    "[project]/Jth/Git Repository/Home/finance-home/app/simulator/page": [
      "static/media/83afe278b6a6bb3c-s.p.3a6ba036.woff2"
    ]
  },
  "appUsingSizeAdjust": true,
  "pages": {},
  "pagesUsingSizeAdjust": false
}